dock_byte/__init__.py
dock_byte/script.py
DOCK_BYTE-0.1.dist-info/LICENSE
DOCK_BYTE-0.1.dist-info/METADATA
DOCK_BYTE-0.1.dist-info/WHEEL
DOCK_BYTE-0.1.dist-info/entry_points.txt
DOCK_BYTE-0.1.dist-info/top_level.txt
DOCK_BYTE-0.1.dist-info/RECORD
