Metadata-Version: 2.1
Name: DOCK-BYTE
Version: 0.1
Summary: A module to extract text from documents and chat with the content.
Home-page: https://github.com/CodeByte-hash/DOCK_BYTE
Author: Muhammad Abdullah
Author-email: abdullahcodewizard@gmail.com
Classifier: Programming Language :: Python :: 3
Classifier: License :: OSI Approved :: MIT License
Classifier: Operating System :: OS Independent
License-File: LICENSE
Requires-Dist: pymupdf
Requires-Dist: pdf2image
Requires-Dist: pytesseract
Requires-Dist: langchain-community
Requires-Dist: streamlit
